elpasado/__init__.py
elpasado/decision.py
elpasado-0.0.7.dist-info/LICENSE
elpasado-0.0.7.dist-info/METADATA
elpasado-0.0.7.dist-info/WHEEL
elpasado-0.0.7.dist-info/top_level.txt
elpasado-0.0.7.dist-info/RECORD
