Metadata-Version: 2.1
Name: elpasado
Version: 0.0.7
Summary: A small example package
Home-page: https://github.com/pypa/sampleproject
Author: ambro17
Author-email: ambro17.1@gmail.com
License: UNKNOWN
Project-URL: Bug Tracker, https://github.com/pypa/sampleproject/issues
Platform: UNKNOWN
Classifier: Programming Language :: Python :: 3
Classifier: License :: OSI Approved :: MIT License
Classifier: Operating System :: OS Independent
Requires-Python: >=3.6
License-File: LICENSE
Requires-Dist: Flask (==1.0.1)
Requires-Dist: requests (<=2.26.0,>=1)
